streamxmlwriter.py
streamxmlwriter.egg-info/PKG-INFO
streamxmlwriter.egg-info/SOURCES.txt
streamxmlwriter.egg-info/dependency_links.txt
streamxmlwriter.egg-info/top_level.txt