Metadata-Version: 1.0
Name: streamxmlwriter
Version: 0.1
Summary: Simple library for incrementally writing XML files of arbitrary size
Home-page: http://github.com/infixfilip/streamxmlwriter/tree/master
Author: Filip Salomonsson
Author-email: filip.salomonsson@gmail.com
License: MIT
Platform: UNKNOWN
Classifier: Development Status :: 3 - Alpha
Classifier: Topic :: Text Processing :: Markup :: XML
